nonebot_plugin_vrchat-0.3.3.dist-info/METADATA
nonebot_plugin_vrchat-0.3.3.dist-info/WHEEL
nonebot_plugin_vrchat-0.3.3.dist-info/entry_points.txt
nonebot_plugin_vrchat-0.3.3.dist-info/licenses/LICENSE
nonebot_plugin_vrchat/__init__.py
nonebot_plugin_vrchat/commands/__init__.py
nonebot_plugin_vrchat/commands/friend.py
nonebot_plugin_vrchat/commands/help.py
nonebot_plugin_vrchat/commands/login.py
nonebot_plugin_vrchat/commands/notifications.py
nonebot_plugin_vrchat/commands/search.py
nonebot_plugin_vrchat/commands/utils.py
nonebot_plugin_vrchat/commands/world.py
nonebot_plugin_vrchat/config.py
nonebot_plugin_vrchat/i18n/.config.json
nonebot_plugin_vrchat/i18n/.lang.schema.json
nonebot_plugin_vrchat/i18n/.template.json
nonebot_plugin_vrchat/i18n/.template.schema.json
nonebot_plugin_vrchat/i18n/__init__.py
nonebot_plugin_vrchat/i18n/en-US.json
nonebot_plugin_vrchat/i18n/ja-JP.json
nonebot_plugin_vrchat/i18n/model.py
nonebot_plugin_vrchat/i18n/types.py
nonebot_plugin_vrchat/i18n/update.txt
nonebot_plugin_vrchat/i18n/utils.py
nonebot_plugin_vrchat/i18n/zh-CN.json
nonebot_plugin_vrchat/img/default.png
nonebot_plugin_vrchat/img/default_img.png
nonebot_plugin_vrchat/img/fa-users-40px.png
nonebot_plugin_vrchat/message/__init__.py
nonebot_plugin_vrchat/message/friend.py
nonebot_plugin_vrchat/message/notifications.py
nonebot_plugin_vrchat/message/templates/default.png
nonebot_plugin_vrchat/message/templates/friend_list.css
nonebot_plugin_vrchat/message/templates/friend_list.html
nonebot_plugin_vrchat/message/templates/friend_list_default.css
nonebot_plugin_vrchat/message/templates/friend_list_default.html
nonebot_plugin_vrchat/message/templates/ntf.css
nonebot_plugin_vrchat/message/templates/ntf.html
nonebot_plugin_vrchat/message/templates/player.css
nonebot_plugin_vrchat/message/templates/player.html
nonebot_plugin_vrchat/message/type.py
nonebot_plugin_vrchat/message/utils.py
nonebot_plugin_vrchat/message/world.py
nonebot_plugin_vrchat/utils.py
nonebot_plugin_vrchat/vrchat/__init__.py
nonebot_plugin_vrchat/vrchat/avatars.py
nonebot_plugin_vrchat/vrchat/client.py
nonebot_plugin_vrchat/vrchat/dict_type.py
nonebot_plugin_vrchat/vrchat/favorites.py
nonebot_plugin_vrchat-0.3.3.dist-info/RECORD
