Metadata-Version: 2.1
Name: nonebot-plugin-vrchat
Version: 0.3.3
Summary: 使用第三方api实现vrchat相关操作,plugin for nonebot2
Keywords: steam,game,vrchat,nonebot2,plugin
Author-Email: Agnes_Digital <Z735803792@163.com>, student_2333 <lgc2333@126.com>
License: MIT
Classifier: License :: OSI Approved :: MIT License
Classifier: Programming Language :: Python
Classifier: Programming Language :: Python :: 3
Classifier: Programming Language :: Python :: 3.9
Classifier: Programming Language :: Python :: 3.10
Classifier: Programming Language :: Python :: 3.11
Classifier: Programming Language :: Python :: 3.12
Classifier: Operating System :: OS Independent
Project-URL: homepage, https://github.com/Agnes4m/nonebot_plugin_vrchat
Requires-Python: <4.0,>=3.9
Requires-Dist: nonebot2>=2.1.0
Requires-Dist: nonebot-plugin-alconna>=0.58.5
Requires-Dist: vrchatapi>=1.19.3
Requires-Dist: httpx>=0.25.0
Requires-Dist: async-lru>=2.0.4
Requires-Dist: nonebot-plugin-session>=0.3.2
Requires-Dist: nonebot-plugin-htmlrender>=0.5.6
Requires-Dist: ruamel-yaml>=0.18.5
Requires-Dist: pydantic>=2.1.1
Requires-Dist: pillow<11.0.0,>=10.0.0
